async_somerandomstuff/__init__.py
async_somerandomstuff.py-0.1.2.dist-info/METADATA
async_somerandomstuff.py-0.1.2.dist-info/WHEEL
async_somerandomstuff.py-0.1.2.dist-info/top_level.txt
async_somerandomstuff.py-0.1.2.dist-info/RECORD
